FlowQ/__init__.py
FlowQ/client/FlowQlient.py
FlowQ/client/__init__.py
FlowQ/cluster/FlowQluster.py
FlowQ/cluster/__init__.py
FlowQ/cluster/__main__.py
FlowQ-0.0.4.dist-info/LICENSE
FlowQ-0.0.4.dist-info/METADATA
FlowQ-0.0.4.dist-info/WHEEL
FlowQ-0.0.4.dist-info/top_level.txt
FlowQ-0.0.4.dist-info/RECORD
