Metadata-Version: 2.1
Name: FlowQ
Version: 0.0.4
Summary: Your Friendly Neighbourhood Distributed Computing System
Author-email: MoltenSteel <stonesteel27@gmail.com>
Project-URL: Homepage, https://github.com/StoneSteel27/FlowQ
Project-URL: Issues, https://github.com/StoneSteel27/FlowQ/issues
Classifier: Programming Language :: Python :: 3
Classifier: License :: OSI Approved :: MIT License
Classifier: Operating System :: OS Independent
Requires-Python: >=3.9
License-File: LICENSE
Requires-Dist: websockets >=12.0
Requires-Dist: requests >=2.31
